MANIFEST.in
README.md
requirements.txt
setup.cfg
setup.py
napalm_vyos/__init__.py
napalm_vyos/vyos.py
napalm_vyos.egg-info/PKG-INFO
napalm_vyos.egg-info/SOURCES.txt
napalm_vyos.egg-info/dependency_links.txt
napalm_vyos.egg-info/requires.txt
napalm_vyos.egg-info/top_level.txt
napalm_vyos/utils/__init__.py