Metadata-Version: 1.1
Name: napalm-vyos
Version: 0.1.5
Summary: Network Automation and Programmability Abstraction Layer with Multivendor support
Home-page: UNKNOWN
Author: Piotr Pieprzycki
Author-email: piotr.pieprzycki@dreamlab.pl
License: UNKNOWN
Platform: UNKNOWN
Classifier: Topic :: Utilities
Classifier: Programming Language :: Python
Classifier: Programming Language :: Python :: 2
Classifier: Programming Language :: Python :: 2.7
Classifier: Operating System :: POSIX :: Linux
Classifier: Operating System :: MacOS
